Metadata-Version: 2.1
Name: ose-workbench-core
Version: 0.1.0a4
Summary: Core library common to all OSE workbenches.
Home-page: https://github.com/gbroques/ose-workbench-core
Author: G Roques
License: UNKNOWN
Platform: UNKNOWN
Classifier: License :: OSI Approved :: GNU Lesser General Public License v2 or later (LGPLv2+)
Classifier: Programming Language :: Python :: 3 :: Only
